AyishaLingxunChuangzaoXinwoXindiqiu/Dockerfile
AyishaLingxunChuangzaoXinwoXindiqiu/README.md
AyishaLingxunChuangzaoXinwoXindiqiu/__init__.py
AyishaLingxunChuangzaoXinwoXindiqiu/__main__.py
AyishaLingxunChuangzaoXinwoXindiqiu/file.epub
AyishaLingxunChuangzaoXinwoXindiqiu/index.html
AyishaLingxunChuangzaoXinwoXindiqiu/css/__init__.py
AyishaLingxunChuangzaoXinwoXindiqiu/css/annotations.css
AyishaLingxunChuangzaoXinwoXindiqiu/css/main.css
AyishaLingxunChuangzaoXinwoXindiqiu/css/normalize.css
AyishaLingxunChuangzaoXinwoXindiqiu/css/popup.css
AyishaLingxunChuangzaoXinwoXindiqiu/font/__init__.py
AyishaLingxunChuangzaoXinwoXindiqiu/font/fontello.eot
AyishaLingxunChuangzaoXinwoXindiqiu/font/fontello.svg
AyishaLingxunChuangzaoXinwoXindiqiu/font/fontello.ttf
AyishaLingxunChuangzaoXinwoXindiqiu/font/fontello.woff
AyishaLingxunChuangzaoXinwoXindiqiu/img/__init__.py
AyishaLingxunChuangzaoXinwoXindiqiu/img/annotator-glyph-sprite.png
AyishaLingxunChuangzaoXinwoXindiqiu/img/annotator-icon-sprite.png
AyishaLingxunChuangzaoXinwoXindiqiu/img/apple-touch-icon.png
AyishaLingxunChuangzaoXinwoXindiqiu/img/cancelfullscreen.png
AyishaLingxunChuangzaoXinwoXindiqiu/img/close.png
AyishaLingxunChuangzaoXinwoXindiqiu/img/fullscreen.png
AyishaLingxunChuangzaoXinwoXindiqiu/img/loader.gif
AyishaLingxunChuangzaoXinwoXindiqiu/img/menu-icon.png
AyishaLingxunChuangzaoXinwoXindiqiu/img/save.png
AyishaLingxunChuangzaoXinwoXindiqiu/img/saved.png
AyishaLingxunChuangzaoXinwoXindiqiu/img/settings-s.png
AyishaLingxunChuangzaoXinwoXindiqiu/img/settings.png
AyishaLingxunChuangzaoXinwoXindiqiu/img/star.png
AyishaLingxunChuangzaoXinwoXindiqiu/js/__init__.py
AyishaLingxunChuangzaoXinwoXindiqiu/js/epub.js
AyishaLingxunChuangzaoXinwoXindiqiu/js/epub.min.js
AyishaLingxunChuangzaoXinwoXindiqiu/js/epub.min.map
AyishaLingxunChuangzaoXinwoXindiqiu/js/hooks.min.js
AyishaLingxunChuangzaoXinwoXindiqiu/js/hooks.min.map
AyishaLingxunChuangzaoXinwoXindiqiu/js/reader.js
AyishaLingxunChuangzaoXinwoXindiqiu/js/reader.js.map
ayisha_lingxun_chuangzao_xinwo_xindiqiu-2022.10.6.0.dist-info/METADATA
ayisha_lingxun_chuangzao_xinwo_xindiqiu-2022.10.6.0.dist-info/WHEEL
ayisha_lingxun_chuangzao_xinwo_xindiqiu-2022.10.6.0.dist-info/entry_points.txt
ayisha_lingxun_chuangzao_xinwo_xindiqiu-2022.10.6.0.dist-info/top_level.txt
ayisha_lingxun_chuangzao_xinwo_xindiqiu-2022.10.6.0.dist-info/RECORD
